LICENSE
README.rst
setup.py
openai_cost_logger/__init__.py
openai_cost_logger/constants.py
openai_cost_logger/openai_cost_logger.py
openai_cost_logger/openai_cost_logger_singleton.py
openai_cost_logger/openai_cost_logger_utils.py
openai_cost_logger/openai_cost_logger_viz.py
openai_cost_logger.egg-info/PKG-INFO
openai_cost_logger.egg-info/SOURCES.txt
openai_cost_logger.egg-info/dependency_links.txt
openai_cost_logger.egg-info/requires.txt
openai_cost_logger.egg-info/top_level.txt