Metadata-Version: 2.1
Name: openai-cost-logger
Version: 0.5.0
Summary: OpenAI Cost Logger
Home-page: https://github.com/drudilorenzo/openai-cost-tracker
Author: Lorenzo Drudi | Mikolaj Boronski | Ivan Zakazov
Author-email: lorenzodrudi11@gmail.com
License: MIT
Keywords: openai,cost,logger,tracker,viz,llms
Platform: UNKNOWN
Requires: openai
Requires: pandas
Requires: matplotlib
License-File: LICENSE
